lab5_part3/group34_lab05_part3/CPU.v
`include "ALU.v"
`include "REGFILE.v"

module cpu(PC,INSTRUCTION,CLK,RESET);
    //Input
    input [31:0] INSTRUCTION;
    input CLK,RESET;

    //output
    output reg [31:0] PC;

    //Wires for reg_file
    wire [2:0] READREG1, READREG2, WRITEREG;
	wire [7:0] REGOUT1, REGOUT2;
	reg WRITEENABLE;

    //Wires for ALU
    wire [7:0] OPERAND1, OPERAND2, ALURESULT;
	reg [2:0] ALUOP;

    //Wires for MUX1
	wire [7:0] negatedOp;
	wire [7:0] registerOp;
	reg signSelect;
	
	//Wires for MUX2
	wire [7:0] IMMEDIATE;
	reg immSelect;
	
	//reg for PC
	reg [31:0] PCreg;
	
	//reg for OPCODE
	reg [7:0] OPCODE;

    //Instantiation reg_file
	reg_file reg_file1(ALURESULT, REGOUT1, REGOUT2, WRITEREG, READREG1, READREG2, WRITEENABLE, CLK, RESET);
	//Instantiation alu
	alu alu1(REGOUT1, OPERAND2, ALURESULT, ALUOP);
	// Instantiation twoscomplement
	twocomp twocomp1(REGOUT2, negatedOp);
	//Instantiation muxs
	mux mux1(REGOUT2, negatedOp, signSelect, registerOp);
	mux mux2(registerOp, IMMEDIATE, immSelect, OPERAND2);

    //Update PC in every positive edge clock cycles
	always @ ( posedge CLK)
	begin
		if (RESET == 1'b1) 
		begin  // Reset the PC counter
			#1;
			PC = 0;	
			PCreg = 0;
		end
		else #1 PC = PCreg;	// Else update the PC counter
	end
	
	
	//Increase the PC counter
	always @ (PC)
	begin
		#1 PCreg = PCreg + 4;
	end

    //Split the instruction word into acording registeraddres and opcodes
    assign READREG1 = INSTRUCTION[15:8];
	assign IMMEDIATE = INSTRUCTION[7:0];
	assign READREG2 = INSTRUCTION[7:0];
	assign WRITEREG = INSTRUCTION[23:16];

    //Controller unit for decoding the instruction
	always @ (INSTRUCTION)
	begin
	
		OPCODE = INSTRUCTION[31:24];	//Extract OPCODE from instruction
		#1	
		//Mux
		case (OPCODE)
		
			//loadi - 0 
			8'b00000000:	begin
								ALUOP = 3'b000;			//Set ALU to forward
								immSelect = 1'b1;		//Set MUX to select immediate value
								signSelect = 1'b0;		//Set sign select MUX to positive sign
								WRITEENABLE = 1'b1;		//Enable writing to register
							end
		
			//mov - 1
			8'b00000001:	begin
								ALUOP = 3'b000;			//Set ALU to FORWARD
								immSelect = 1'b0;		//Set MUX to select register input
								signSelect = 1'b0;		//Set sign select MUX to positive sign
								WRITEENABLE = 1'b1;		//Enable writing to register
							end
			
			//add - 2
			8'b00000010:	begin
								ALUOP = 3'b001;			//Set ALU to ADD
								immSelect = 1'b0;		//Set MUX to select register input
								signSelect = 1'b0;		//Set sign select MUX to positive sign
								WRITEENABLE = 1'b1;		//Enable writing to register
							end	
		
			//sub - 3
			8'b00000011:	begin
								ALUOP = 3'b001;			//Set ALU to ADD
								immSelect = 1'b0;		//Set MUX to select register input
								signSelect = 1'b1;		//Set sign select MUX to negative sign
								WRITEENABLE = 1'b1;		//Enable writing to register
							end

			//and - 4
			8'b00000100:	begin
								ALUOP = 3'b010;			//Set ALU to AND
								immSelect = 1'b0;		//Set MUX to select register input
								signSelect = 1'b0;		//Set sign select MUX to positive sign
								WRITEENABLE = 1'b1;		//Enable writing to register
							end
							
			//or - 5
			8'b00000101:	begin
								ALUOP = 3'b011;			//Set ALU to OR
								immSelect = 1'b0;		//Set MUX to select register input
								signSelect = 1'b0;		//Set sign select MUX to positive sign
								WRITEENABLE = 1'b1;		//Enable writing to register
							end

		endcase
		
	end

endmodule


// This module calculates 2nd's complement
module twocomp(IN, OUT);

	//Input
	input [7:0] IN;

    //Output
	output [7:0] OUT;
	
	//Calculate 2nd's complement
	assign #1 OUT = ~IN + 1;

endmodule

module mux(IN1, IN2, SELECT, OUT);

	//Input
	input [7:0] IN1, IN2;
	input SELECT;

    //Output
	output reg [7:0] OUT;
	
	//Select input acroding to select bit
	always @ (IN1, IN2, SELECT)
	begin
		if (SELECT == 1'b1)		//Select input 2
		begin
			OUT = IN2;
		end
		else					//Select input 1
		begin
			OUT = IN1;
		end
	end

endmodule

lab5_part3/group34_lab05_part3/ALU.v
module alu(DATA1, DATA2, RESULT, SELECT);
    // Defining ports
    input [7:0] DATA1, DATA2;
    output [7:0] RESULT;
    input [2:0] SELECT;
    reg [7:0] RESULT;

    // Wires for the different cases
    wire [7:0] C0 , C1 , C2, C3 ;
    
    // Forward
    FORWARD case0(DATA1, DATA2,C0);

    // Add
    ADD case1(DATA1,DATA2,C1);

    // AND
    AND case2(DATA1,DATA2,C2);

    // OR
    OR case3(DATA1,DATA2,C3);


    always @*
    // Defining each case
    begin
        case(SELECT)
        //mov, loadi
        3'b000:
            begin
                RESULT = C0;
            end

        //add
        3'b001:
            begin
                RESULT = C1;
            end

        //bitwise and
        3'b010:
            begin
                RESULT = C2;
            end

        //bitwise or
        3'b011:
            begin
                RESULT = C3;
            end

        //reserved
        3'b1xx:
            begin
            ;
            end
        default: RESULT = DATA2 ;
        endcase
    end
endmodule

// This module forwards the second operand to the result
module FORWARD(DATA1, DATA2, RESULT);
    input [7:0] DATA1 , DATA2 ;
    output [7:0] RESULT;
    assign #1 RESULT = DATA2;
endmodule

// This module adds the two operands
module  ADD(DATA1, DATA2, RESULT);
    input [7:0] DATA1 , DATA2 ;
    output [7:0] RESULT;
    assign #2 RESULT = DATA1 + DATA2;
endmodule

// This module returns the bitwise-AND product of two operands
module AND(DATA1, DATA2, RESULT);
    input [7:0] DATA1 , DATA2 ;
    output [7:0] RESULT;
    assign #1 RESULT = DATA1 & DATA2;
endmodule

// This module returns the bitwise-OR product of two operands
module OR(DATA1, DATA2, RESULT);
    input [7:0] DATA1 , DATA2 ;
    output [7:0] RESULT;
    assign #1 RESULT = DATA1 | DATA2;
endmodule

lab5_part3/group34_lab05_part3/REGFILE.v
module reg_file(IN,OUT1,OUT2,INADDRESS,OUT1ADDRESS,OUT2ADDRESS, WRITE, CLK, RESET);

    // Defining Ports 
    input [7:0] IN; // The data input port
    input [2:0] INADDRESS; //The address of the register to write to
    
    output [7:0] OUT1, OUT2; // The data output ports
    input [2:0] OUT1ADDRESS, OUT2ADDRESS; // The address of the registers to read from
    //reg [7:0] OUT1, OUT2;



    input WRITE; // The write enable signal
    input CLK; // The clock signal
    input RESET; // The reset signal

    reg [7:0] registers[7:0]; // The array of 8-bit registers



    // Asynchronously assigning OUT1 and OUT2
    assign #2 OUT1 = registers[OUT1ADDRESS];
    assign #2 OUT2 = registers[OUT2ADDRESS];

    // Positive Edge Triggered
    // All operations happenat the positive edge of the clock
    always @(posedge CLK)
    begin

        // When RESET signal is HIGH , all registers should be cleared (written zero)
        if (RESET) //RESET Block 
            begin
                #1;// Writinh required a delay of 1 second
                for(integer i = 0; i < 8; i++) // For-loop to iterate through the array of registers
                begin
                    //$display("Clock");
                    registers[i] = 0;
                end
            end
        

        // When WRITE signal is HIGH, data in input port IN should be written to registers[INADDRESS]
        else if (WRITE) //WRITE Block
            begin
                //$display("Write");
                #1; // Writing requires a delay of 1 time unit
                registers[INADDRESS] = IN;
            end        
    end
    
    initial
    begin
        $dumpfile("Write.vcd");	
        for(integer i=0; i<8; i++)
        begin
            $dumpvars(0,registers[i]);
        end
    end
endmodule

lab5_part3/group34_lab05_part3/cpu_tb.v
 // Computer Architecture (CO224) - Lab 05
// Design: Testbench of Integrated CPU of Simple Processor
// Author: Isuru Nawinne
`include "CPU.v"

module cpu_tb;

    reg CLK, RESET;
    wire [31:0] PC;
    wire [31:0] INSTRUCTION;
    
    /* 
    ------------------------
     SIMPLE INSTRUCTION MEM
    ------------------------
    */
    
    // TODO: Initialize an array of registers (8x1024) named 'instr_mem' to be used as instruction memory
    reg [7:0] instr_mem [1023:0];

    // TODO: Create combinational logic to support CPU instruction fetching, given the Program Counter(PC) value 
    //       (make sure you include the delay for instruction fetching here)
    assign #2 INSTRUCTION = {instr_mem[PC+3], instr_mem[PC+2], instr_mem[PC+1], instr_mem[PC]};
    
    initial
    begin
        // Initialize instruction memory with the set of instructions you need execute on CPU
        
        // METHOD 1: manually loading instructions to instr_mem
        //{instr_mem[10'd3], instr_mem[10'd2], instr_mem[10'd1], instr_mem[10'd0]} = 32'b00000000000001000000000000000101;
        //{instr_mem[10'd7], instr_mem[10'd6], instr_mem[10'd5], instr_mem[10'd4]} = 32'b00000000000000100000000000001001;
        //{instr_mem[10'd11], instr_mem[10'd10], instr_mem[10'd9], instr_mem[10'd8]} = 32'b00000010000001100000010000000010;
        
        // METHOD 2: loading instr_mem content from instr_mem.mem file
        $readmemb("instr_mem.mem", instr_mem);
    end
    
    /* 
    -----
     CPU
    -----
    */
    cpu mycpu(PC, INSTRUCTION, CLK, RESET);

    initial
    begin
    
        // generate files needed to plot the waveform using GTKWave
        $dumpfile("cpu_wavedata.vcd");

		$dumpvars(0, cpu_tb);
        
        CLK = 1'b0;
        RESET = 1'b0;
        
        // TODO: Reset the CPU (by giving a pulse to RESET signal) to start the program execution
        RESET = 1'b1;
        #5
        RESET = 1'b0;
        
        // finish simulation after some time
        #60
        $finish;
        
    end
    
    // clock signal generation
    always
        #4 CLK = ~CLK;
        

endmodule

lab5_part3/group34_lab05_part3/Write.vcd
$date
	Wed May 24 10:56:29 2023
$end
$version
	Icarus Verilog
$end
$timescale
	1s
$end
$scope module cpu_tb $end
$scope module mycpu $end
$scope module reg_file1 $end
$var reg 8 ! \registers[0] [7:0] $end
$upscope $end
$upscope $end
$upscope $end
$scope module cpu_tb $end
$scope module mycpu $end
$scope module reg_file1 $end
$var reg 8 " \registers[1] [7:0] $end
$upscope $end
$upscope $end
$upscope $end
$scope module cpu_tb $end
$scope module mycpu $end
$scope module reg_file1 $end
$var reg 8 # \registers[2] [7:0] $end
$upscope $end
$upscope $end
$upscope $end
$scope module cpu_tb $end
$scope module mycpu $end
$scope module reg_file1 $end
$var reg 8 $ \registers[3] [7:0] $end
$upscope $end
$upscope $end
$upscope $end
$scope module cpu_tb $end
$scope module mycpu $end
$scope module reg_file1 $end
$var reg 8 % \registers[4] [7:0] $end
$upscope $end
$upscope $end
$upscope $end
$scope module cpu_tb $end
$scope module mycpu $end
$scope module reg_file1 $end
$var reg 8 & \registers[5] [7:0] $end
$upscope $end
$upscope $end
$upscope $end
$scope module cpu_tb $end
$scope module mycpu $end
$scope module reg_file1 $end
$var reg 8 ' \registers[6] [7:0] $end
$upscope $end
$upscope $end
$upscope $end
$scope module cpu_tb $end
$scope module mycpu $end
$scope module reg_file1 $end
$var reg 8 ( \registers[7] [7:0] $end
$upscope $end
$upscope $end
$upscope $end
$scope module cpu_tb $end
$var wire 32 ) PC [31:0] $end
$var wire 32 * INSTRUCTION [31:0] $end
$var reg 1 + CLK $end
$var reg 1 , RESET $end
$scope module mycpu $end
$var wire 1 + CLK $end
$var wire 32 - INSTRUCTION [31:0] $end
$var wire 1 , RESET $end
$var wire 8 . registerOp [7:0] $end
$var wire 8 / negatedOp [7:0] $end
$var wire 3 0 WRITEREG [2:0] $end
$var wire 8 1 REGOUT2 [7:0] $end
$var wire 8 2 REGOUT1 [7:0] $end
$var wire 3 3 READREG2 [2:0] $end
$var wire 3 4 READREG1 [2:0] $end
$var wire 8 5 OPERAND2 [7:0] $end
$var wire 8 6 IMMEDIATE [7:0] $end
$var wire 8 7 ALURESULT [7:0] $end
$var reg 3 8 ALUOP [2:0] $end
$var reg 8 9 OPCODE [7:0] $end
$var reg 32 : PC [31:0] $end
$var reg 32 ; PCreg [31:0] $end
$var reg 1 < WRITEENABLE $end
$var reg 1 = immSelect $end
$var reg 1 > signSelect $end
$scope module alu1 $end
$var wire 3 ? SELECT [2:0] $end
$var wire 8 @ DATA2 [7:0] $end
$var wire 8 A DATA1 [7:0] $end
$var wire 8 B C3 [7:0] $end
$var wire 8 C C2 [7:0] $end
$var wire 8 D C1 [7:0] $end
$var wire 8 E C0 [7:0] $end
$var reg 8 F RESULT [7:0] $end
$scope module case0 $end
$var wire 8 G RESULT [7:0] $end
$var wire 8 H DATA2 [7:0] $end
$var wire 8 I DATA1 [7:0] $end
$upscope $end
$scope module case1 $end
$var wire 8 J RESULT [7:0] $end
$var wire 8 K DATA2 [7:0] $end
$var wire 8 L DATA1 [7:0] $end
$upscope $end
$scope module case2 $end
$var wire 8 M RESULT [7:0] $end
$var wire 8 N DATA2 [7:0] $end
$var wire 8 O DATA1 [7:0] $end
$upscope $end
$scope module case3 $end
$var wire 8 P RESULT [7:0] $end
$var wire 8 Q DATA2 [7:0] $end
$var wire 8 R DATA1 [7:0] $end
$upscope $end
$upscope $end
$scope module mux1 $end
$var wire 1 > SELECT $end
$var wire 8 S IN2 [7:0] $end
$var wire 8 T IN1 [7:0] $end
$var reg 8 U OUT [7:0] $end
$upscope $end
$scope module mux2 $end
$var wire 8 V IN1 [7:0] $end
$var wire 8 W IN2 [7:0] $end
$var wire 1 = SELECT $end
$var reg 8 X OUT [7:0] $end
$upscope $end
$scope module reg_file1 $end
$var wire 1 + CLK $end
$var wire 8 Y IN [7:0] $end
$var wire 3 Z INADDRESS [2:0] $end
$var wire 8 [ OUT1 [7:0] $end
$var wire 3 \ OUT1ADDRESS [2:0] $end
$var wire 8 ] OUT2 [7:0] $end
$var wire 3 ^ OUT2ADDRESS [2:0] $end
$var wire 1 , RESET $end
$var wire 1 < WRITE $end
$scope begin $ivl_for_loop0 $end
$var integer 32 _ i [31:0] $end
$upscope $end
$scope begin $ivl_for_loop1 $end
$var integer 32 ` i [31:0] $end
$upscope $end
$upscope $end
$scope module twocomp1 $end
$var wire 8 a IN [7:0] $end
$var wire 8 b OUT [7:0] $end
$upscope $end
$upscope $end
$upscope $end
$enddefinitions $end
#0
$dumpvars
bx b
bx a
b1000 `
bx _
bx ^
bx ]
bx \
bx [
bx Z
bx Y
bx X
bx W
bx V
bx U
bx T
bx S
bx R
bx Q
bx P
bx O
bx N
bx M
bx L
bx K
bx J
bx I
bx H
bx G
bx F
bx E
bx D
bx C
bx B
bx A
bx @
bx ?
x>
x=
x<
bx ;
bx :
bx 9
bx 8
bx 7
bx 6
bx 5
bx 4
bx 3
bx 2
bx 1
bx 0
bx /
bx .
bx -
1,
0+
bx *
bx )
bx (
bx '
bx &
bx %
bx $
bx #
bx "
bx !
$end
#4
1+
#5
b0 (
b0 '
b0 &
b0 %
b0 $
b0 #
b0 "
b0 !
b1000 _
b0 ;
b0 )
b0 :
0,
#6
b100 ;
#7
b0 4
b0 \
b101 3
b101 ^
b0 0
b0 Z
b0 9
b101 6
b101 W
b101 *
b101 -
#8
b101 5
b101 @
b101 H
b101 K
b101 N
b101 Q
b101 X
1<
0>
1=
b0 8
b0 ?
0+
#9
b101 7
b101 F
b101 Y
b0 .
b0 U
b0 V
bx1x1 B
bx1x1 P
b0x0x C
b0x0x M
b101 E
b101 G
b0 2
b0 A
b0 I
b0 L
b0 O
b0 R
b0 [
b0 1
b0 T
b0 ]
b0 a
#10
b101 B
b101 P
b0 C
b0 M
b0 /
b0 S
b0 b
#11
b101 D
b101 J
#12
1+
#13
b100 )
b100 :
b101 !
#14
b1000 ;
#15
b1001 5
b1001 @
b1001 H
b1001 K
b1001 N
b1001 Q
b1001 X
b1 3
b1 ^
b1 0
b1 Z
b1001 6
b1001 W
b10000000000001001 *
b10000000000001001 -
b101 2
b101 A
b101 I
b101 L
b101 O
b101 R
b101 [
#16
b1001 7
b1001 F
b1001 Y
b1101 B
b1101 P
b1001 E
b1001 G
b1 C
b1 M
0+
#17
b1110 D
b1110 J
#20
1+
#21
b1001 "
b1000 )
b1000 :
#22
b1100 ;
#23
b1 5
b1 @
b1 H
b1 K
b1 N
b1 Q
b1 X
b10 0
b10 Z
b1001 .
b1001 U
b1001 V
b1 9
b1 6
b1 W
b1001 1
b1001 T
b1001 ]
b1001 a
b1000000100000000000000001 *
b1000000100000000000000001 -
#24
b1 7
b1 F
b1 Y
b1001 5
b1001 @
b1001 H
b1001 K
b1001 N
b1001 Q
b1001 X
b101 B
b101 P
b1 E
b1 G
b11110111 /
b11110111 S
b11110111 b
0=
0+
#25
b1001 7
b1001 F
b1001 Y
b1101 B
b1101 P
b1001 E
b1001 G
#28
1+
#29
b1100 )
b1100 :
b1001 #
#30
b10000 ;
#31
b10 4
b10 \
b0 3
b0 ^
b11 0
b11 Z
b10 9
b0 6
b0 W
b10000000110000001000000000 *
b10000000110000001000000000 -
#32
b1110 7
b1110 F
b1110 Y
b1 8
b1 ?
0+
#33
b101 5
b101 @
b101 H
b101 K
b101 N
b101 Q
b101 X
b101 .
b101 U
b101 V
b1001 2
b1001 A
b1001 I
b1001 L
b1001 O
b1001 R
b1001 [
b101 1
b101 T
b101 ]
b101 a
#34
b101 E
b101 G
b11111011 /
b11111011 S
b11111011 b
#36
1+
#37
b1110 $
b10000 )
b10000 :
#38
b10100 ;
#39
b11 4
b11 \
b1 3
b1 ^
b100 0
b100 Z
b11 9
b1 6
b1 W
b11000001000000001100000001 *
b11000001000000001100000001 -
#40
b11111011 5
b11111011 @
b11111011 H
b11111011 K
b11111011 N
b11111011 Q
b11111011 X
b11111011 .
b11111011 U
b11111011 V
1>
0+
#41
b11111011 B
b11111011 P
b1001 C
b1001 M
b11111011 E
b11111011 G
b1110 2
b1110 A
b1110 I
b1110 L
b1110 O
b1110 R
b1110 [
b1001 1
b1001 T
b1001 ]
b1001 a
#42
b11110111 5
b11110111 @
b11110111 H
b11110111 K
b11110111 N
b11110111 Q
b11110111 X
b11110111 .
b11110111 U
b11110111 V
b11111111 B
b11111111 P
b1010 C
b1010 M
b11110111 /
b11110111 S
b11110111 b
#43
b110 C
b110 M
b11110111 E
b11110111 G
#44
b101 7
b101 F
b101 Y
b101 D
b101 J
1+
#45
b10100 )
b10100 :
b101 %
#46
b11000 ;
#47
b0 4
b0 \
b101 3
b101 ^
b0 0
b0 Z
b0 9
b1110101 6
b1110101 W
b1110101 *
b1110101 -
#48
b1001 .
b1001 U
b1001 V
b1110101 5
b1110101 @
b1110101 H
b1110101 K
b1110101 N
b1110101 Q
b1110101 X
b11110111 7
b11110111 F
b11110111 Y
0>
1=
b0 8
b0 ?
0+
#49
b1110101 7
b1110101 F
b1110101 Y
b0 .
b0 U
b0 V
b1111111 B
b1111111 P
b100 C
b100 M
b1110101 E
b1110101 G
b101 2
b101 A
b101 I
b101 L
b101 O
b101 R
b101 [
b0 1
b0 T
b0 ]
b0 a
#50
b1110101 B
b1110101 P
b101 C
b101 M
b0 /
b0 S
b0 b
#51
b1111010 D
b1111010 J
#52
1+
#53
b1110101 !
b11000 )
b11000 :
#54
b11100 ;
#55
b10010010 5
b10010010 @
b10010010 H
b10010010 K
b10010010 N
b10010010 Q
b10010010 X
b10 3
b10 ^
b1 0
b1 Z
b10010010 6
b10010010 W
b1110101 2
b1110101 A
b1110101 I
b1110101 L
b1110101 O
b1110101 R
b1110101 [
b10000000010010010 *
b10000000010010010 -
#56
b10010010 7
b10010010 F
b10010010 Y
b11110111 B
b11110111 P
b10010010 E
b10010010 G
b10000 C
b10000 M
0+
#57
b1001 .
b1001 U
b1001 V
b1001 1
b1001 T
b1001 ]
b1001 a
b111 D
b111 J
#58
b11110111 /
b11110111 S
b11110111 b
#60
1+
#61
b11100 )
b11100 :
b10010010 "
#62
b100000 ;
#63
b1 4
b1 \
b0 5
b0 @
b0 H
b0 K
b0 N
b0 Q
b0 X
b0 3
b0 ^
b101 0
b101 Z
b100 9
b0 6
b0 W
b100000001010000000100000000 *
b100000001010000000100000000 -
#64
b1001 5
b1001 @
b1001 H
b1001 K
b1001 N
b1001 Q
b1001 X
b0 7
b0 F
b0 Y
b1110101 B
b1110101 P
b0 C
b0 M
b0 E
b0 G
0=
b10 8
b10 ?
0+
#65
b1110101 5
b1110101 @
b1110101 H
b1110101 K
b1110101 N
b1110101 Q
b1110101 X
b1 7
b1 F
b1 Y
b1110101 .
b1110101 U
b1110101 V
b1111101 B
b1111101 P
b1 C
b1 M
b1001 E
b1001 G
b10010010 2
b10010010 A
b10010010 I
b10010010 L
b10010010 O
b10010010 R
b10010010 [
b1110101 1
b1110101 T
b1110101 ]
b1110101 a
